pyrae/__init__.py
pyrae/core.py
pyrae/dle.py
pyrae/logger.py
pyrae/util.py
pyrae-0.1.4.dist-info/LICENSE
pyrae-0.1.4.dist-info/METADATA
pyrae-0.1.4.dist-info/WHEEL
pyrae-0.1.4.dist-info/top_level.txt
pyrae-0.1.4.dist-info/RECORD
