Metadata-Version: 2.1
Name: pyrae
Version: 0.1.4
Summary: Perform searches against the RAE dictionary.
Home-page: https://github.com/nachocho/pyrae
Author: Javier Treviño
Author-email: javier.trevino@gmail.com
License: MIT
Platform: UNKNOWN
Classifier: Development Status :: 3 - Alpha
Classifier: Programming Language :: Python :: 3.6
Classifier: License :: OSI Approved :: MIT License
Classifier: Operating System :: OS Independent
Requires-Python: >=3.6
License-File: LICENSE
Requires-Dist: beautifulsoup4
Requires-Dist: dogpile.cache
